Metadata-Version: 2.1
Name: queuepy
Version: 1.0.1
Summary: Simple module to create queues
Home-page: https://github.com/synnkfps/PyQueue
Author: SynnK
Author-email: 
License: MIT
Platform: UNKNOWN
Classifier: License :: OSI Approved :: MIT License
Classifier: Programming Language :: Python :: 3.10
